setup.cfg
setup.py
Flask_Sleepy.egg-info/PKG-INFO
Flask_Sleepy.egg-info/SOURCES.txt
Flask_Sleepy.egg-info/dependency_links.txt
Flask_Sleepy.egg-info/not-zip-safe
Flask_Sleepy.egg-info/requires.txt
Flask_Sleepy.egg-info/top_level.txt
sleepy/__init__.py
sleepy/adapter.py
sleepy/core.py
sleepy/exceptions.py
sleepy/routing.py
sleepy/views.py