Metadata-Version: 1.1
Name: Flask-Sleepy
Version: 0.3.0
Summary: REST is hard. Let's go shopping
Home-page: https://git.prior-it.be/Prior-IT/flask-sleepy
Author: Robin Ramael
Author-email: robin.ramael@gmail.com
License: UNKNOWN
Download-URL: https://git.prior-it.be/Prior-IT/flask-sleepy/archive/0.3.0.tar.gz
Keywords: flask,rest,api,marshmallow,sqlalchemy,restful
Platform: UNKNOWN
